Metadata-Version: 1.0
Name: mrdistributions
Version: 1.0
Summary: Gaussian and Binomail distributions
Home-page: UNKNOWN
Author: MILIND RAJ
Author-email: milindraj003@gmail.com
License: UNKNOWN
Platform: UNKNOWN
